{
    "key": "group_5f8cfc410f00b",
    "title": "Carreras",
    "fields": [
        {
            "key": "field_607870408b37f",
            "label": "Icono",
            "name": "icon",
            "type": "image",
            "instructions": "",
            "required": 0,
            "conditional_logic": 0,
            "wrapper": {
                "width": "",
                "class": "",
                "id": ""
            },
            "return_format": "url",
            "preview_size": "medium",
            "library": "all",
            "min_width": "",
            "min_height": "",
            "min_size": "",
            "max_width": "",
            "max_height": "",
            "max_size": "",
            "mime_types": ""
        },
        {
            "key": "field_5fcb116efdd82",
            "label": "Trailer de la carrera",
            "name": "trailer_video",
            "type": "url",
            "instructions": "",
            "required": 0,
            "conditional_logic": 0,
            "wrapper": {
                "width": "",
                "class": "",
                "id": ""
            },
            "default_value": "",
            "placeholder": ""
        },
        {
            "key": "field_5fca905734e75",
            "label": "Cursos",
            "name": "courses",
            "type": "relationship",
            "instructions": "",
            "required": 0,
            "conditional_logic": 0,
            "wrapper": {
                "width": "",
                "class": "",
                "id": ""
            },
            "post_type": [
                "sfwd-courses"
            ],
            "taxonomy": "",
            "filters": [
                "search",
                "taxonomy"
            ],
            "elements": "",
            "min": "",
            "max": "",
            "return_format": "object"
        },
        {
            "key": "field_611b33ae35b87",
            "label": "Duración total",
            "name": "duration",
            "type": "text",
            "instructions": "Formato: xh Ymin. Si este valor no existe se intenta agarrar los de los cursos y sumarlos",
            "required": 0,
            "conditional_logic": 0,
            "wrapper": {
                "width": "",
                "class": "",
                "id": ""
            },
            "default_value": "",
            "placeholder": "",
            "prepend": "",
            "append": "",
            "maxlength": ""
        },
        {
            "key": "field_5f8cfd88782b0",
            "label": "Product WC",
            "name": "wc_product",
            "type": "post_object",
            "instructions": "",
            "required": 0,
            "conditional_logic": 0,
            "wrapper": {
                "width": "",
                "class": "",
                "id": ""
            },
            "post_type": [
                "product"
            ],
            "taxonomy": "",
            "allow_null": 1,
            "multiple": 0,
            "return_format": "object",
            "ui": 1
        },
        {
            "key": "field_60959582b7edb",
            "label": "Tiene mentorias opcionales",
            "name": "has_mentorships",
            "type": "true_false",
            "instructions": "",
            "required": 0,
            "conditional_logic": 0,
            "wrapper": {
                "width": "",
                "class": "",
                "id": ""
            },
            "message": "",
            "default_value": 0,
            "ui": 0,
            "ui_on_text": "",
            "ui_off_text": ""
        },
        {
            "key": "field_609595a0b7edc",
            "label": "Info de mentorías",
            "name": "mentorship",
            "type": "group",
            "instructions": "",
            "required": 0,
            "conditional_logic": [
                [
                    {
                        "field": "field_60959582b7edb",
                        "operator": "==",
                        "value": "1"
                    }
                ]
            ],
            "wrapper": {
                "width": "",
                "class": "",
                "id": ""
            },
            "layout": "block",
            "sub_fields": [
                {
                    "key": "field_609597afb7edf",
                    "label": "semanas de mentoría",
                    "name": "weeks",
                    "type": "number",
                    "instructions": "",
                    "required": 0,
                    "conditional_logic": 0,
                    "wrapper": {
                        "width": "",
                        "class": "",
                        "id": ""
                    },
                    "default_value": "",
                    "placeholder": "",
                    "prepend": "",
                    "append": "",
                    "min": "",
                    "max": "",
                    "step": ""
                },
                {
                    "key": "field_609597bab7ee0",
                    "label": "WC Producto",
                    "name": "wc_career_mentorship",
                    "type": "post_object",
                    "instructions": "",
                    "required": 0,
                    "conditional_logic": 0,
                    "wrapper": {
                        "width": "",
                        "class": "",
                        "id": ""
                    },
                    "post_type": [
                        "product"
                    ],
                    "taxonomy": "",
                    "allow_null": 0,
                    "multiple": 0,
                    "return_format": "id",
                    "ui": 1
                }
            ]
        },
        {
            "key": "field_5f8cfdbb782b1",
            "label": "Partner",
            "name": "partner",
            "type": "image",
            "instructions": "",
            "required": 0,
            "conditional_logic": 0,
            "wrapper": {
                "width": "",
                "class": "",
                "id": ""
            },
            "return_format": "array",
            "preview_size": "medium",
            "library": "all",
            "min_width": "",
            "min_height": "",
            "min_size": "",
            "max_width": "",
            "max_height": "",
            "max_size": "",
            "mime_types": ""
        },
        {
            "key": "field_5f8cfdd3782b2",
            "label": "Instructores",
            "name": "teachers",
            "type": "relationship",
            "instructions": "",
            "required": 0,
            "conditional_logic": 0,
            "wrapper": {
                "width": "",
                "class": "",
                "id": ""
            },
            "post_type": [
                "teacher"
            ],
            "taxonomy": "",
            "filters": [
                "search",
                "post_type",
                "taxonomy"
            ],
            "elements": [
                "featured_image"
            ],
            "min": "",
            "max": "",
            "return_format": "object"
        },
        {
            "key": "field_5f8cff24782b3",
            "label": "info",
            "name": "info",
            "type": "group",
            "instructions": "",
            "required": 0,
            "conditional_logic": 0,
            "wrapper": {
                "width": "",
                "class": "",
                "id": ""
            },
            "layout": "block",
            "sub_fields": [
                {
                    "key": "field_5f8cff2c782b4",
                    "label": "Subtitulo",
                    "name": "subtitle",
                    "type": "text",
                    "instructions": "",
                    "required": 0,
                    "conditional_logic": 0,
                    "wrapper": {
                        "width": "",
                        "class": "",
                        "id": ""
                    },
                    "default_value": "",
                    "placeholder": "",
                    "prepend": "",
                    "append": "",
                    "maxlength": ""
                },
                {
                    "key": "field_5f8cff40782b6",
                    "label": "Imagen fondo mentores",
                    "name": "bgimg_teachers",
                    "type": "image",
                    "instructions": "",
                    "required": 0,
                    "conditional_logic": 0,
                    "wrapper": {
                        "width": "",
                        "class": "",
                        "id": ""
                    },
                    "return_format": "url",
                    "preview_size": "medium",
                    "library": "all",
                    "min_width": "",
                    "min_height": "",
                    "min_size": "",
                    "max_width": 1200,
                    "max_height": "",
                    "max_size": "",
                    "mime_types": ""
                },
                {
                    "key": "field_5fca9036ba06d",
                    "label": "Qué vas a aprender?",
                    "name": "objectives",
                    "type": "repeater",
                    "instructions": "",
                    "required": 0,
                    "conditional_logic": 0,
                    "wrapper": {
                        "width": "",
                        "class": "",
                        "id": ""
                    },
                    "collapsed": "field_5fca9043ba06e",
                    "min": 0,
                    "max": 0,
                    "layout": "table",
                    "button_label": "",
                    "sub_fields": [
                        {
                            "key": "field_5fca9043ba06e",
                            "label": "item",
                            "name": "item",
                            "type": "text",
                            "instructions": "",
                            "required": 0,
                            "conditional_logic": 0,
                            "wrapper": {
                                "width": "",
                                "class": "",
                                "id": ""
                            },
                            "default_value": "",
                            "placeholder": "",
                            "prepend": "",
                            "append": "",
                            "maxlength": ""
                        }
                    ]
                },
                {
                    "key": "field_60f3a01a4f1b5",
                    "label": "Recursos descargables",
                    "name": "resources",
                    "type": "number",
                    "instructions": "",
                    "required": 0,
                    "conditional_logic": 0,
                    "wrapper": {
                        "width": "",
                        "class": "",
                        "id": ""
                    },
                    "default_value": "",
                    "placeholder": "",
                    "prepend": "",
                    "append": "",
                    "min": "",
                    "max": "",
                    "step": ""
                }
            ]
        },
        {
            "key": "field_5fb5d4c9dc4b3",
            "label": "Testimonios de Carrera",
            "name": "testimonials",
            "type": "relationship",
            "instructions": "",
            "required": 0,
            "conditional_logic": 0,
            "wrapper": {
                "width": "",
                "class": "",
                "id": ""
            },
            "post_type": [
                "testimonial"
            ],
            "taxonomy": "",
            "filters": "",
            "elements": "",
            "min": "",
            "max": 0,
            "return_format": "object"
        }
    ],
    "location": [
        [
            {
                "param": "post_type",
                "operator": "==",
                "value": "career"
            }
        ]
    ],
    "menu_order": 1,
    "position": "normal",
    "style": "default",
    "label_placement": "top",
    "instruction_placement": "label",
    "hide_on_screen": [
        "discussion",
        "comments"
    ],
    "active": true,
    "description": "",
    "modified": 1629172701
}